var Karen_Shelton_Field_Hockey_Stadium = {
"type": "FeatureCollection",
"crs": { "type": "name", "properties": { "name": "urn:ogc:def:crs:OGC:1.3:CRS84" } },
"features": [
{ "type": "Feature", "properties": { "id": 1, "descrip": "KarenSheltonFieldHockeyStadium" }, "geometry": { "type": "Point", "coordinates": [ -79.04428, 35.90521] } }
]
}
